pyopspec/__init__.py
pyopspec/config.py
pyopspec/exceptions.py
pyopspec/process_config.py
pyopspec/pyopspec.py
pyopspec/data_exporters/__init__.py
pyopspec/data_exporters/data_exporter.py
pyopspec/furnace/__init__.py
pyopspec/furnace/exceptions.py
pyopspec/furnace/furnace_controller.py
pyopspec/furnace/logging.py
pyopspec/furnace/watlow_furnace_controller.py
pyopspec/mass_flow_controller/__init__.py
pyopspec/mass_flow_controller/bronkhorst_mass_flow_controller.py
pyopspec/mass_flow_controller/exceptions.py
pyopspec/mass_flow_controller/logging.py
pyopspec/mass_flow_controller/mass_flow_controller.py
pyopspec/plotters/__init__.py
pyopspec/plotters/data.py
pyopspec/plotters/logging.py
pyopspec/plotters/non_blocking_plotter.py
pyopspec/plotters/point.py
pyopspec/plotters/process_plotter.py
pyopspec/pressure_controller/__init__.py
pyopspec/pressure_controller/bronkhorst_pressure_controller.py
pyopspec/pressure_controller/exceptions.py
pyopspec/pressure_controller/logging.py
pyopspec/pressure_controller/pressure_controller.py
pyopspec/steps/__init__.py
pyopspec/steps/cooling_step.py
pyopspec/steps/final_step.py
pyopspec/steps/heating_step.py
pyopspec/steps/isothermal_step.py
pyopspec/steps/pressure_ramp_step.py
pyopspec-1.0.2.dist-info/METADATA
pyopspec-1.0.2.dist-info/WHEEL
pyopspec-1.0.2.dist-info/entry_points.txt
pyopspec-1.0.2.dist-info/top_level.txt
pyopspec-1.0.2.dist-info/RECORD
